README.md
setup.py
cxplain/__init__.py
cxplain/explanation_model.py
cxplain.egg-info/PKG-INFO
cxplain.egg-info/SOURCES.txt
cxplain.egg-info/dependency_links.txt
cxplain.egg-info/requires.txt
cxplain.egg-info/top_level.txt
cxplain/backend/__init__.py
cxplain/backend/causal_loss.py
cxplain/backend/numpy_math_interface.py
cxplain/backend/tensorflow_cxplain.py
cxplain/backend/tf_math_interface.py
cxplain/backend/validation.py
cxplain/backend/masking/__init__.py
cxplain/backend/masking/base_masking.py
cxplain/backend/masking/masking_util.py
cxplain/backend/masking/word_drop_masking.py
cxplain/backend/masking/zero_masking.py
cxplain/backend/model_builders/__init__.py
cxplain/backend/model_builders/base_model_builder.py
cxplain/backend/model_builders/mlp.py
cxplain/backend/model_builders/rnn.py
cxplain/backend/model_builders/unet.py
cxplain/backend/serialisation/__init__.py
cxplain/backend/serialisation/model_serialiser.py
cxplain/backend/serialisation/pickle_model_serialisation.py
cxplain/backend/serialisation/tf_model_serialisation.py
cxplain/util/__init__.py
cxplain/util/count_vectoriser.py
cxplain/util/test_util.py
cxplain/visualisation/__init__.py
cxplain/visualisation/plot.py
tests/__init__.py
tests/test_causal_loss.py
tests/test_explanation_model.py
tests/test_masking.py
tests/test_plot.py
tests/test_uncertainty.py
tests/test_validation.py