Metadata-Version: 2.1
Name: cxplain
Version: 1.0.3
Summary: UNKNOWN
Home-page: http://schwabpatrick.com
Author: Patrick Schwab
Author-email: patrick.schwab@hest.ethz.ch
License: MIT License
Platform: UNKNOWN
Classifier: License :: OSI Approved :: MIT License
Classifier: Operating System :: OS Independent
